sympla_tools/__init__.py
sympla_tools/scripts/__init__.py
sympla_tools/scripts/build_binary.py
sympla_tools/tests/__init__.py
sympla_tools/tests/performance_test.py
sympla_tools/tests/validate_signature_test.py
sympla_tools/tickets/__init__.py
sympla_tools/tickets/signature/__init__.py
sympla_tools/tickets/signature/__main__.py
sympla_tools/tickets/signature/ethereum_token.py
sympla_tools-0.3.1.dist-info/METADATA
sympla_tools-0.3.1.dist-info/WHEEL
sympla_tools-0.3.1.dist-info/entry_points.txt
sympla_tools-0.3.1.dist-info/RECORD
