Metadata-Version: 2.1
Name: sympla-tools
Version: 0.3.1
Summary: SDK para integração com a API da Sympla
Author: Maicol K. Oliveira
Author-email: tbh.maicol.oliveira@sympla.com.br
Requires-Python: ==3.10.14
Classifier: Programming Language :: Python :: 3
Requires-Dist: ecdsa (>=0.19.0,<0.20.0)
Requires-Dist: eth-account (>=0.13.4,<0.14.0)
Requires-Dist: pyinstaller (>=6.11.1,<7.0.0)
Requires-Dist: pysha3 (>=1.0.2,<2.0.0)
Requires-Dist: pytest-benchmark (>=5.1.0,<6.0.0)
Requires-Dist: web3 (>=7.5.0,<8.0.0)
